{"is_source_file": true, "file_id": 60, "git_revision": "", "state": 1, "description": "", "external_files": [], "external_methods": [], "published": [], "classes": [], "methods": [], "calls": [], "search-terms": [], "ctags": [{"_type": "tag", "name": "getMapsProvider", "path": "/home/kavia/workspace/code-generation/foodie-connect-183050-183059/frontend_web_app/src/services/geo.js", "pattern": "/^export function getMapsProvider() {$/", "language": "JavaScript", "kind": "function", "signature": "()"}], "format": "JavaScript", "hash": "72b098d59bb71d1b4e4838c2242d1078", "format-version": 4, "code-base-name": "frontend_web_app", "filename": "frontend_web_app/src/services/geo.js", "knowledge_revision": 105}